{"info": {"address1": "44370 Old Warm Springs Boulevard", "city": "Fremont", "state": "CA", "zip": "94538", "country": "United States", "phone": "510 668 0881", "website": "https://www.abvcpharma.com", "industry": "Biotechnology", "industryKey": "biotechnology", "industryDisp": "Biotechnology", "sector": "Healthcare", "sectorKey": "healthcare", "sectorDisp": "Healthcare", "longBusinessSummary": "ABVC BioPharma, Inc., a clinical-stage biopharmaceutical company, develops drugs and medical devices to fulfill unmet medical needs in the United States. The company is developing ABV-1501, which is in Phase II clinical trials as a combination therapy for triple negative breast cancer; ABV-1504, which has completed Phase II clinical trials for depressive disorders; ABV-1505, which is in Phase II clinical trials for adult attention deficit hyperactivity disorder; ABV-1702, which is in Phase II clinical trials to treat myelodysplastic syndromes; and ABV-1601, which is in Phase I/II clinical trials for treating depression in cancer patients. It is also developing ABV-1701 Vitargus, which is in Phase II clinical trials for the treatment of retinal detachment or vitreous hemorrhage; ABV-1519, which is in Phase I/II clinical trials for the treatment of non-small cell lung cancer; ABV-2001, an intraocular irrigation solution; ABV-2002, a corneal Storage Solution; and ABV-1703, which is in Phase II clinical trials for the treatment of metastatic pancreatic cancer. ABVC BioPharma, Inc. has a co-development agreement with Rgene Corporation and collaboration agreements with BioHopeKing Corporation and BioFirst Corporation. The company is based in Fremont, California. ABVC BioPharma, Inc. operates as a subsidiary of YuanGene Corporation.", "fullTimeEmployees": 16, "companyOfficers": [{"maxAge": 1, "name": "Mr. Eugene  Jiang", "age": 38, "title": "Chairman & Chief Business Officer", "yearBorn": 1986, "fiscalYear": 2024, "totalPay": 200000, "exercisedValue": 0, "unexercisedValue": 0}, {"maxAge": 1, "name": "Dr. Uttam Yashwant Patil Ph.D.", "age": 38, "title": "CEO & Interim CFO", "yearBorn": 1986, "fiscalYear": 2024, "exercisedValue": 0, "unexercisedValue": 0}, {"maxAge": 1, "name": "Dr. Tsung-Shann  Jiang EMBA, Ph.D.", "age": 70, "title": "Chief Scientific Officer, Chief Strategy Officer & Director", "yearBorn": 1954, "fiscalYear": 2024, "totalPay": 200000, "exercisedValue": 0, "unexercisedValue": 0}], "compensationAsOfEpochDate": 1735603200, "executiveTeam": [], "maxAge": 86400, "priceHint": 4, "previousClose": 2.9, "open": 2.78, "dayLow": 2.78, "dayHigh": 2.96, "regularMarketPreviousClose": 2.9, "regularMarketOpen": 2.78, "regularMarketDayLow": 2.78, "regularMarketDayHigh": 2.96, "payoutRatio": 0.0, "beta": 0.242, "forwardPE": -6.636364, "volume": 60549, "regularMarketVolume": 60549, "averageVolume": 85149, "averageVolume10days": 57990, "averageDailyVolume10Day": 57990, "bid": 2.8, "ask": 3.64, "bidSize": 1, "askSize": 2, "marketCap": 68742128, "fiftyTwoWeekLow": 0.4, "fiftyTwoWeekHigh": 5.48, "allTimeHigh": 7165605.0, "allTimeLow": 0.343949, "priceToSalesTrailing12Months": 86.152084, "fiftyDayAverage": 2.9358, "twoHundredDayAverage": 2.03257, "trailingAnnualDividendRate": 0.0, "trailingAnnualDividendYield": 0.0, "currency": "USD", "tradeable": false, "enterpriseValue": 71342272, "profitMargins": 0.0, "floatShares": 20163210, "sharesOutstanding": 23541824, "sharesShort": 390678, "sharesShortPriorMonth": 635557, "sharesShortPreviousMonthDate": 1759190400, "dateShortInterest": 1761868800, "sharesPercentSharesOut": 0.0166, "heldPercentInsiders": 0.11366, "heldPercentInstitutions": 0.03232, "shortRatio": 4.84, "shortPercentOfFloat": 0.0188, "impliedSharesOutstanding": 23541824, "bookValue": 0.498, "priceToBook": 5.863454, "lastFiscalYearEnd": 1735603200, "nextFiscalYearEnd": 1767139200, "mostRecentQuarter": 1759190400, "netIncomeToCommon": -5077184, "trailingEps": -0.25, "forwardEps": -0.44, "lastSplitFactor": "1:10", "lastSplitDate": 1690243200, "enterpriseToRevenue": 89.411, "enterpriseToEbitda": -14.619, "52WeekChange": 4.1146383, "SandP52WeekChange": 0.1276468, "quoteType": "EQUITY", "currentPrice": 2.92, "recommendationKey": "none", "totalCash": 257243, "totalCashPerShare": 0.011, "ebitda": -4880031, "totalDebt": 2472189, "quickRatio": 0.04, "currentRatio": 0.626, "totalRevenue": 797916, "debtToEquity": 17.058, "revenuePerShare": 0.046, "returnOnAssets": -0.17221001, "returnOnEquity": -0.47713003, "grossProfits": 797916, "freeCashflow": -1543949, "operatingCashflow": -2269398, "revenueGrowth": 1.045, "grossMargins": 1.0, "ebitdaMargins": 0.0, "operatingMargins": -1.4651899, "financialCurrency": "USD", "symbol": "ABVC", "language": "en-US", "region": "US", "typeDisp": "Equity", "quoteSourceName": "Nasdaq Real Time Price", "triggerable": true, "customPriceAlertConfidence": "HIGH", "corporateActions": [], "postMarketTime": 1763500204, "regularMarketTime": 1763499601, "exchange": "NCM", "messageBoardId": "finmb_325748154", "exchangeTimezoneName": "America/New_York", "exchangeTimezoneShortName": "EST", "gmtOffSetMilliseconds": -18000000, "market": "us_market", "esgPopulated": false, "regularMarketChangePercent": 0.689654, "regularMarketPrice": 2.92, "shortName": "ABVC Biopharma, Inc.", "marketState": "PREPRE", "fiftyDayAverageChange": -0.0158, "fiftyDayAverageChangePercent": -0.0053818375, "twoHundredDayAverageChange": 0.8874302, "twoHundredDayAverageChangePercent": 0.436605, "sourceInterval": 15, "exchangeDataDelayedBy": 0, "ipoExpectedDate": "2021-08-03", "prevName": "American BriVision (Holding) Corporation", "nameChangeDate": "2025-11-18", "cryptoTradeable": false, "hasPrePostMarketData": true, "firstTradeDateMilliseconds": 1100097000000, "postMarketChangePercent": 0.0, "postMarketPrice": 2.92, "postMarketChange": 0.0, "regularMarketChange": 0.02, "regularMarketDayRange": "2.78 - 2.96", "fullExchangeName": "NasdaqCM", "averageDailyVolume3Month": 85149, "fiftyTwoWeekLowChange": 2.52, "fiftyTwoWeekLowChangePercent": 6.2999997, "fiftyTwoWeekRange": "0.4 - 5.48", "fiftyTwoWeekHighChange": -2.56, "fiftyTwoWeekHighChangePercent": -0.46715328, "fiftyTwoWeekChangePercent": 411.46384, "dividendDate": 1557273600, "earningsTimestampStart": 1754996340, "earningsTimestampEnd": 1755518400, "isEarningsDateEstimate": true, "epsTrailingTwelveMonths": -0.25, "epsForward": -0.44, "longName": "ABVC BioPharma, Inc.", "displayName": "ABVC BioPharma", "trailingPegRatio": null}, "info_ts": "2025-11-19T07:12:28.115550+00:00"}