{"info": {"address1": "76 Blanchard Road", "city": "Burlington", "state": "MA", "zip": "01803", "country": "United States", "phone": "781 687 0300", "website": "https://www.aware.com", "industry": "Software - Application", "industryKey": "software-application", "industryDisp": "Software - Application", "sector": "Technology", "sectorKey": "technology", "sectorDisp": "Technology", "longBusinessSummary": "Aware, Inc., a biometric identity platform company, provides biometrics software products and services for government agencies and commercial entities in the United States, the United Kingdom, and internationally. The company offers biometric software solution, including Knomi, a mobile biometric authentication framework which provides multiple biometric modality options; AwareABIS, an automated biometric identification system used for large-scale biometric identification and deduplication; AFIX suite used for small-scale law enforcement focused biometric identification; and AFIX Tracker for fingerprint, palmprint, and latent print identification, as well as AFIX Face, AFIX Verifier, AFIX Identifier, AFIX Comparator, AFIX Engine, and AFIX NIST Transaction Engine. It also provides BioSP, a biometric integration platform-as-a-service that enables biometric data processing and management functionality in a web services architecture; WebEnroll, a browser-based biometric enrollment and data management solution; and AwareID, a software-as-a-service that provides identity verification and continuous authentication capabilities. In addition, the company offers biometrics applications, such as Nexa line, a biometric search and match SDKs including Nexa Fingerprint, Nexa Face, Nexa Iris, and Nexa Voice; and AwareXM, an interoperable fingerprint matching SDK that provides fingerprint minutiae extraction, template generation, and fingerprint authentication. Further, it sells imaging products used in medical and advanced imaging applications; and offers software maintenance, program management, and software engineering services. The company sells its products and services through systems integrators, original equipment manufacturers (OEMs), value added resellers, partners, and directly to select end user customers. Aware, Inc. was incorporated in 1986 and is headquartered in Burlington, Massachusetts.", "fullTimeEmployees": 64, "companyOfficers": [{"maxAge": 1, "name": "Mr. David K. Traverse", "age": 50, "title": "CFO & Treasurer", "yearBorn": 1974, "fiscalYear": 2024, "totalPay": 393522, "exercisedValue": 0, "unexercisedValue": 0}, {"maxAge": 1, "name": "Dr. Mohamed  Lazzouni Ph.D.", "age": 64, "title": "Chief Technology Officer", "yearBorn": 1960, "fiscalYear": 2024, "totalPay": 347159, "exercisedValue": 0, "unexercisedValue": 0}, {"maxAge": 1, "name": "Mr. Ajay K. Amlani", "age": 49, "title": "CEO, President & Director", "yearBorn": 1975, "fiscalYear": 2024, "exercisedValue": 0, "unexercisedValue": 0}, {"maxAge": 1, "name": "Ms. Sarah  Eckert Esq.", "title": "Senior Legal Counsel & Corporate Secretary", "fiscalYear": 2024, "exercisedValue": 0, "unexercisedValue": 0}, {"maxAge": 1, "name": "Ms. Lona  Therrien", "title": "Chief Marketing Officer", "fiscalYear": 2024, "exercisedValue": 0, "unexercisedValue": 0}, {"maxAge": 1, "name": "Ms. Lindsey  Savarino", "title": "Vice President of Human Resources", "fiscalYear": 2024, "exercisedValue": 0, "unexercisedValue": 0}, {"maxAge": 1, "name": "Mr. Brian J. Krause", "age": 46, "title": "Chief Revenue Officer", "yearBorn": 1978, "fiscalYear": 2024, "exercisedValue": 0, "unexercisedValue": 0}], "compensationAsOfEpochDate": 1735603200, "irWebsite": "http://ir.aware.com/", "executiveTeam": [], "maxAge": 86400, "priceHint": 4, "previousClose": 2.23, "open": 2.21, "dayLow": 2.19, "dayHigh": 2.27, "regularMarketPreviousClose": 2.23, "regularMarketOpen": 2.21, "regularMarketDayLow": 2.19, "regularMarketDayHigh": 2.27, "exDividendDate": 1406246400, "payoutRatio": 0.0, "beta": 0.815, "forwardPE": -17.0, "volume": 32082, "regularMarketVolume": 32082, "averageVolume": 37423, "averageVolume10days": 36500, "averageDailyVolume10Day": 36500, "bid": 2.43, "ask": 2.36, "bidSize": 1, "askSize": 1, "marketCap": 47235868, "fiftyTwoWeekLow": 1.37, "fiftyTwoWeekHigh": 2.95, "allTimeHigh": 87.125, "allTimeLow": 1.05, "priceToSalesTrailing12Months": 2.7103436, "fiftyDayAverage": 2.4862, "twoHundredDayAverage": 1.9976, "trailingAnnualDividendRate": 0.0, "trailingAnnualDividendYield": 0.0, "currency": "USD", "tradeable": false, "enterpriseValue": 28779868, "profitMargins": -0.32184, "floatShares": 11895744, "sharesOutstanding": 21373696, "sharesShort": 45682, "sharesShortPriorMonth": 65618, "sharesShortPreviousMonthDate": 1759190400, "dateShortInterest": 1761868800, "sharesPercentSharesOut": 0.0021, "heldPercentInsiders": 0.44324002, "heldPercentInstitutions": 0.18857999, "shortRatio": 1.69, "shortPercentOfFloat": 0.0061000003, "impliedSharesOutstanding": 21373696, "bookValue": 1.275, "priceToBook": 1.7333333, "lastFiscalYearEnd": 1735603200, "nextFiscalYearEnd": 1767139200, "mostRecentQuarter": 1759190400, "netIncomeToCommon": -5609000, "trailingEps": -0.27, "forwardEps": -0.13, "enterpriseToRevenue": 1.651, "enterpriseToEbitda": -4.791, "52WeekChange": 0.47682118, "SandP52WeekChange": 0.1276468, "lastDividendValue": 1.75, "lastDividendDate": 1406246400, "quoteType": "EQUITY", "currentPrice": 2.21, "recommendationKey": "none", "totalCash": 22500000, "totalCashPerShare": 1.053, "ebitda": -6007000, "totalDebt": 4044000, "quickRatio": 3.187, "currentRatio": 3.364, "totalRevenue": 17428000, "debtToEquity": 14.847, "revenuePerShare": 0.823, "returnOnAssets": -0.0979, "returnOnEquity": -0.18972, "grossProfits": 16038000, "freeCashflow": -3023875, "operatingCashflow": -5761000, "revenueGrowth": 0.333, "grossMargins": 0.92024004, "ebitdaMargins": -0.34467998, "operatingMargins": -0.25249, "financialCurrency": "USD", "symbol": "AWRE", "language": "en-US", "region": "US", "typeDisp": "Equity", "quoteSourceName": "Nasdaq Real Time Price", "triggerable": true, "customPriceAlertConfidence": "HIGH", "marketState": "PREPRE", "corporateActions": [], "postMarketTime": 1763509381, "regularMarketTime": 1763499600, "exchange": "NGM", "messageBoardId": "finmb_348808", "exchangeTimezoneName": "America/New_York", "exchangeTimezoneShortName": "EST", "gmtOffSetMilliseconds": -18000000, "market": "us_market", "esgPopulated": false, "regularMarketChangePercent": -0.89686, "regularMarketPrice": 2.21, "hasPrePostMarketData": true, "firstTradeDateMilliseconds": 839597400000, "postMarketChangePercent": 0.45248824, "postMarketPrice": 2.22, "postMarketChange": 0.00999999, "regularMarketChange": -0.02, "regularMarketDayRange": "2.19 - 2.27", "fullExchangeName": "NasdaqGM", "averageDailyVolume3Month": 37423, "fiftyTwoWeekLowChange": 0.84000003, "fiftyTwoWeekLowChangePercent": 0.61313874, "fiftyTwoWeekRange": "1.37 - 2.95", "fiftyTwoWeekHighChange": -0.74, "fiftyTwoWeekHighChangePercent": -0.25084746, "fiftyTwoWeekChangePercent": 47.682117, "dividendDate": 1406160000, "earningsTimestamp": 1761768000, "earningsTimestampStart": 1761768000, "earningsTimestampEnd": 1761768000, "earningsCallTimestampStart": 1761771600, "earningsCallTimestampEnd": 1761771600, "isEarningsDateEstimate": false, "epsTrailingTwelveMonths": -0.27, "epsForward": -0.13, "fiftyDayAverageChange": -0.27620006, "fiftyDayAverageChangePercent": -0.11109325, "twoHundredDayAverageChange": 0.21240008, "twoHundredDayAverageChangePercent": 0.10632764, "sourceInterval": 15, "exchangeDataDelayedBy": 0, "cryptoTradeable": false, "shortName": "Aware, Inc.", "longName": "Aware, Inc.", "displayName": "Aware", "trailingPegRatio": null}, "info_ts": "2025-11-19T07:12:47.513547+00:00"}