{"info": {"address1": "4450 Excelsior Boulevard", "address2": "Suite 100", "city": "Saint Louis Park", "state": "MN", "zip": "55416", "country": "United States", "phone": "952 893 6868", "website": "https://www.bridgewaterbankmn.com", "industry": "Banks - Regional", "industryKey": "banks-regional", "industryDisp": "Banks - Regional", "sector": "Financial Services", "sectorKey": "financial-services", "sectorDisp": "Financial Services", "longBusinessSummary": "Bridgewater Bancshares, Inc. operates as the bank holding company for Bridgewater Bank that provides banking products and services in the United States. The company offers commercial loans, including loans secured by nonfarm, nonresidential properties, multifamily residential properties, and nonowner occupied single family residential properties; construction, land development, and commercial and industrial loans; commercial real estate loans, such as owner and nonowner occupied properties; single family residential construction, land development, finished lots and raw land, and commercial and multifamily construction loans, as well as paycheck protection program loans. It also provides deposit products, including savings and money market accounts, demand deposits, time and brokered deposits, and interest and noninterest bearing transaction accounts, as well as certificates of deposit. In addition, the company offers online, mobile, and direct banking services. The company was incorporated in 2005 and is headquartered in Saint Louis Park, Minnesota.", "fullTimeEmployees": 325, "companyOfficers": [{"maxAge": 1, "name": "Mr. Gerald John Baack", "age": 57, "title": "CEO, Founder & Non Independent Executive Chairman", "yearBorn": 1967, "fiscalYear": 2024, "totalPay": 916989, "exercisedValue": 0, "unexercisedValue": 944350}, {"maxAge": 1, "name": "Mr. Joseph M. Chybowski", "age": 37, "title": "President & CFO", "yearBorn": 1987, "fiscalYear": 2024, "totalPay": 604828, "exercisedValue": 0, "unexercisedValue": 904470}, {"maxAge": 1, "name": "Mr. Jeffrey D. Shellberg", "age": 62, "title": "Co-Founder, EVP, Deputy Chief Credit Officer, Secretary & Non Independent Executive Director", "yearBorn": 1962, "fiscalYear": 2024, "totalPay": 508431, "exercisedValue": 0, "unexercisedValue": 920750}, {"maxAge": 1, "name": "Mr. Nicholas L. Place", "age": 39, "title": "Chief Banking Officer", "yearBorn": 1985, "fiscalYear": 2024, "totalPay": 489393, "exercisedValue": 100200, "unexercisedValue": 918390}, {"maxAge": 1, "name": "Ms. Mary Jayne Crocker", "age": 62, "title": "Executive VP & Chief Strategy Officer", "yearBorn": 1962, "fiscalYear": 2024, "totalPay": 553547, "exercisedValue": 0, "unexercisedValue": 921930}, {"maxAge": 1, "name": "Ms. Lisa M. Salazar", "age": 51, "title": "Chief Operating Officer", "yearBorn": 1973, "fiscalYear": 2024, "exercisedValue": 0, "unexercisedValue": 0}, {"maxAge": 1, "name": "Ms. Laura  Espeseth", "age": 42, "title": "Chief Administrative Officer", "yearBorn": 1982, "fiscalYear": 2024, "exercisedValue": 0, "unexercisedValue": 0}, {"maxAge": 1, "name": "Mr. Justin  Horstman", "title": "Director of Investor Relations", "fiscalYear": 2024, "exercisedValue": 0, "unexercisedValue": 0}, {"maxAge": 1, "name": "Mr. Ben M. Klocke J.D.", "title": "General Counsel", "fiscalYear": 2024, "exercisedValue": 0, "unexercisedValue": 0}, {"maxAge": 1, "name": "Mr. Daniel D. Poppe", "age": 76, "title": "Senior VP of Commercial Banking", "yearBorn": 1948, "fiscalYear": 2024, "exercisedValue": 0, "unexercisedValue": 0}], "auditRisk": 5, "boardRisk": 6, "compensationRisk": 7, "shareHolderRightsRisk": 3, "overallRisk": 5, "governanceEpochDate": 1761955200, "compensationAsOfEpochDate": 1735603200, "executiveTeam": [], "maxAge": 86400, "priceHint": 2, "previousClose": 16.33, "open": 16.26, "dayLow": 16.17, "dayHigh": 16.46, "regularMarketPreviousClose": 16.33, "regularMarketOpen": 16.26, "regularMarketDayLow": 16.17, "regularMarketDayHigh": 16.46, "payoutRatio": 0.0, "beta": 0.655, "trailingPE": 12.343512, "forwardPE": 12.438462, "volume": 46019, "regularMarketVolume": 48400, "averageVolume": 107681, "averageVolume10days": 76960, "averageDailyVolume10Day": 76960, "bid": 16.13, "ask": 16.26, "bidSize": 1, "askSize": 1, "marketCap": 446045120, "fiftyTwoWeekLow": 11.93, "fiftyTwoWeekHigh": 18.007, "allTimeHigh": 20.205, "allTimeLow": 7.9, "priceToSalesTrailing12Months": 3.505459, "fiftyDayAverage": 16.9577, "twoHundredDayAverage": 15.492425, "trailingAnnualDividendRate": 0.0, "trailingAnnualDividendYield": 0.0, "currency": "USD", "tradeable": false, "enterpriseValue": 875193664, "profitMargins": 0.32189, "floatShares": 21931793, "sharesOutstanding": 27584732, "sharesShort": 261096, "sharesShortPriorMonth": 162348, "sharesShortPreviousMonthDate": 1759190400, "dateShortInterest": 1761868800, "sharesPercentSharesOut": 0.0095, "heldPercentInsiders": 0.20575, "heldPercentInstitutions": 0.64812, "shortRatio": 1.98, "shortPercentOfFloat": 0.0117999995, "impliedSharesOutstanding": 27584732, "bookValue": 15.623, "priceToBook": 1.0350125, "lastFiscalYearEnd": 1735603200, "nextFiscalYearEnd": 1767139200, "mostRecentQuarter": 1759190400, "earningsQuarterlyGrowth": 0.337, "netIncomeToCommon": 36904000, "trailingEps": 1.31, "forwardEps": 1.3, "enterpriseToRevenue": 6.878, "52WeekChange": 0.10263336, "SandP52WeekChange": 0.1276716, "quoteType": "EQUITY", "currentPrice": 16.17, "targetHighPrice": 21.0, "targetLowPrice": 20.0, "targetMeanPrice": 20.66667, "targetMedianPrice": 21.0, "recommendationKey": "none", "numberOfAnalystOpinions": 3, "totalCash": 167128000, "totalCashPerShare": 6.059, "totalDebt": 525348992, "totalRevenue": 127243000, "revenuePerShare": 4.627, "returnOnAssets": 0.00815, "returnOnEquity": 0.086260006, "grossProfits": 127243000, "operatingCashflow": 55412000, "earningsGrowth": 0.407, "revenueGrowth": 0.292, "grossMargins": 0.0, "ebitdaMargins": 0.0, "operatingMargins": 0.45935002, "financialCurrency": "USD", "symbol": "BWB", "language": "en-US", "region": "US", "typeDisp": "Equity", "quoteSourceName": "Nasdaq Real Time Price", "triggerable": true, "customPriceAlertConfidence": "HIGH", "corporateActions": [], "postMarketTime": 1763507434, "regularMarketTime": 1763499601, "exchange": "NCM", "messageBoardId": "finmb_24588031", "exchangeTimezoneName": "America/New_York", "exchangeTimezoneShortName": "EST", "gmtOffSetMilliseconds": -18000000, "market": "us_market", "esgPopulated": false, "regularMarketChangePercent": -0.9797908, "regularMarketPrice": 16.17, "shortName": "Bridgewater Bancshares, Inc.", "marketState": "POST", "priceEpsCurrentYear": 10.8766575, "fiftyDayAverageChange": -0.78770065, "fiftyDayAverageChangePercent": -0.046450913, "twoHundredDayAverageChange": 0.6775751, "twoHundredDayAverageChangePercent": 0.0437359, "sourceInterval": 15, "exchangeDataDelayedBy": 0, "cryptoTradeable": false, "hasPrePostMarketData": true, "firstTradeDateMilliseconds": 1521034200000, "postMarketChangePercent": 0.0, "postMarketPrice": 16.17, "postMarketChange": 0.0, "regularMarketChange": -0.15999985, "regularMarketDayRange": "16.17 - 16.46", "fullExchangeName": "NasdaqCM", "averageDailyVolume3Month": 107681, "fiftyTwoWeekLowChange": 4.24, "fiftyTwoWeekLowChangePercent": 0.35540652, "fiftyTwoWeekRange": "11.93 - 18.007", "fiftyTwoWeekHighChange": -1.8369999, "fiftyTwoWeekHighChangePercent": -0.102015875, "fiftyTwoWeekChangePercent": 10.263336, "earningsTimestamp": 1761076800, "earningsTimestampStart": 1769634000, "earningsTimestampEnd": 1769634000, "earningsCallTimestampStart": 1761138000, "earningsCallTimestampEnd": 1761138000, "isEarningsDateEstimate": true, "epsTrailingTwelveMonths": 1.31, "epsForward": 1.3, "epsCurrentYear": 1.48667, "longName": "Bridgewater Bancshares, Inc.", "displayName": "Bridgewater Bancshares", "trailingPegRatio": null}, "info_ts": "2025-11-19T00:45:14.688045+00:00"}