{"info": {"address1": "600 Steamboat Road", "address2": "Suite 202", "city": "Greenwich", "state": "CT", "zip": "06830", "country": "United States", "phone": "203 340 8500", "industry": "Asset Management", "industryKey": "asset-management", "industryDisp": "Asset Management", "sector": "Financial Services", "sectorKey": "financial-services", "sectorDisp": "Financial Services", "companyOfficers": [{"maxAge": 1, "name": "Mr. Thomas Philip Majewski CPA", "age": 49, "title": "Chairperson & CEO", "yearBorn": 1975, "fiscalYear": 2024, "exercisedValue": 0, "unexercisedValue": 0}, {"maxAge": 1, "name": "Mr. Nauman S. Malik J.D.", "age": 44, "title": "Chief Compliance Officer", "yearBorn": 1980, "fiscalYear": 2024, "exercisedValue": 0, "unexercisedValue": 0}, {"maxAge": 1, "name": "Ms. Courtney Barrett Fandrick", "age": 42, "title": "Secretary", "yearBorn": 1982, "fiscalYear": 2024, "exercisedValue": 0, "unexercisedValue": 0}], "compensationAsOfEpochDate": 1735603200, "executiveTeam": [], "maxAge": 86400, "priceHint": 2, "previousClose": 11.4, "open": 11.35, "dayLow": 11.22, "dayHigh": 11.4239, "regularMarketPreviousClose": 11.4, "regularMarketOpen": 11.35, "regularMarketDayLow": 11.22, "regularMarketDayHigh": 11.4239, "dividendRate": 1.32, "dividendYield": 11.65, "exDividendDate": 1765411200, "payoutRatio": 1.8203, "trailingPE": 8.8515625, "forwardPE": 5.810256, "volume": 252984, "regularMarketVolume": 252984, "averageVolume": 151700, "averageVolume10days": 181500, "averageDailyVolume10Day": 181500, "bid": 0.0, "ask": 0.0, "bidSize": 200, "askSize": 400, "marketCap": 300408160, "fiftyTwoWeekLow": 11.22, "fiftyTwoWeekHigh": 16.39, "allTimeHigh": 20.47, "allTimeLow": 5.62, "priceToSalesTrailing12Months": 5.069119, "fiftyDayAverage": 12.73, "twoHundredDayAverage": 13.78174, "trailingAnnualDividendRate": 0.6, "trailingAnnualDividendYield": 0.052631583, "currency": "USD", "tradeable": false, "enterpriseValue": 434081376, "profitMargins": 0.47994, "sharesOutstanding": 26514399, "sharesShort": 65868, "sharesShortPriorMonth": 106236, "sharesShortPreviousMonthDate": 1759190400, "dateShortInterest": 1761868800, "sharesPercentSharesOut": 0.0025, "heldPercentInsiders": 0.14561, "heldPercentInstitutions": 0.12162, "shortRatio": 0.46, "shortPercentOfFloat": 0.0029, "impliedSharesOutstanding": 26514399, "bookValue": 14.211, "priceToBook": 0.7972697, "lastFiscalYearEnd": 1735603200, "nextFiscalYearEnd": 1767139200, "mostRecentQuarter": 1759190400, "earningsQuarterlyGrowth": 9.624, "netIncomeToCommon": 28442552, "trailingEps": 1.28, "forwardEps": 1.95, "enterpriseToRevenue": 7.325, "52WeekChange": -0.27434754, "SandP52WeekChange": 0.1276468, "lastDividendValue": 0.13, "lastDividendDate": 1754870400, "quoteType": "EQUITY", "currentPrice": 11.33, "targetHighPrice": 15.0, "targetLowPrice": 13.0, "targetMeanPrice": 14.33333, "targetMedianPrice": 15.0, "recommendationMean": 1.0, "recommendationKey": "strong_buy", "numberOfAnalystOpinions": 3, "totalCash": 41269092, "totalCashPerShare": 1.65, "totalDebt": 191920240, "quickRatio": 3.581, "currentRatio": 3.601, "totalRevenue": 59262400, "debtToEquity": 53.986, "revenuePerShare": 2.369, "returnOnAssets": 0.06321, "returnOnEquity": 0.09, "grossProfits": 59262400, "freeCashflow": 32381432, "operatingCashflow": -77195376, "earningsGrowth": 6.883, "revenueGrowth": 0.294, "grossMargins": 1.0, "ebitdaMargins": 0.0, "operatingMargins": 0.81452006, "financialCurrency": "USD", "symbol": "EIC", "language": "en-US", "region": "US", "typeDisp": "Equity", "quoteSourceName": "Delayed Quote", "triggerable": true, "customPriceAlertConfidence": "HIGH", "corporateActions": [{"header": "Dividend", "message": "EIC announced a cash dividend of 0.13 with an ex-date of Dec. 11, 2025", "meta": {"eventType": "DIVIDEND", "dateEpochMs": 1765429200000, "amount": "0.13"}}], "postMarketTime": 1763509801, "regularMarketTime": 1763499602, "hasPrePostMarketData": true, "firstTradeDateMilliseconds": 1563975000000, "marketState": "PREPRE", "longName": "Eagle Point Income Company Inc.", "postMarketChangePercent": 0.0, "postMarketPrice": 11.33, "postMarketChange": 0.0, "regularMarketChange": -0.0699997, "regularMarketDayRange": "11.22 - 11.4239", "fullExchangeName": "NYSE", "averageDailyVolume3Month": 151700, "fiftyTwoWeekLowChange": 0.10999966, "fiftyTwoWeekLowChangePercent": 0.009803891, "fiftyTwoWeekRange": "11.22 - 16.39", "fiftyTwoWeekHighChange": -5.0599995, "fiftyTwoWeekHighChangePercent": -0.30872482, "fiftyTwoWeekChangePercent": -27.434753, "earningsTimestampStart": 1754310600, "earningsTimestampEnd": 1754656200, "earningsCallTimestampStart": 1748446200, "earningsCallTimestampEnd": 1748446200, "isEarningsDateEstimate": true, "epsTrailingTwelveMonths": 1.28, "epsForward": 1.95, "epsCurrentYear": 1.49, "priceEpsCurrentYear": 7.604027, "fiftyDayAverageChange": -1.3999996, "fiftyDayAverageChangePercent": -0.10997641, "twoHundredDayAverageChange": -2.4517403, "twoHundredDayAverageChangePercent": -0.17789772, "sourceInterval": 15, "exchangeDataDelayedBy": 0, "averageAnalystRating": "1.0 - Strong Buy", "cryptoTradeable": false, "shortName": "Eagle Point Income Company Inc.", "exchange": "NYQ", "messageBoardId": "finmb_573895193", "exchangeTimezoneName": "America/New_York", "exchangeTimezoneShortName": "EST", "gmtOffSetMilliseconds": -18000000, "market": "us_market", "esgPopulated": false, "regularMarketChangePercent": -0.614032, "regularMarketPrice": 11.33, "displayName": "Eagle Point Income Company", "trailingPegRatio": null}, "info_ts": "2025-11-19T06:50:08.985723+00:00"}