{"info": {"address1": "9115 West Russell Road", "address2": "Suite 110", "city": "Las Vegas", "state": "NV", "zip": "89148", "country": "United States", "phone": "702 851 4200", "website": "https://www.gbankfinancialholdings.com", "industry": "Banks - Regional", "industryKey": "banks-regional", "industryDisp": "Banks - Regional", "sector": "Financial Services", "sectorKey": "financial-services", "sectorDisp": "Financial Services", "longBusinessSummary": "GBank Financial Holdings Inc. operates as a bank holding company for GBank that provides banking services to commercial and consumer customers in Nevada. The company offers business and personal checking and savings accounts. It also provides small business administration loans; commercial real estate, equipment, business term, and medical/professional loans; business lines of credit; accounts receivable/inventory financing services; and credit cards. In addition, the company offers account and cash management services. The company was founded in 2007 and is based in Las Vegas, Nevada.", "fullTimeEmployees": 187, "companyOfficers": [{"maxAge": 1, "name": "Mr. Edward M. Nigro", "age": 81, "title": "CEO & Executive Chairman", "yearBorn": 1943, "fiscalYear": 2024, "totalPay": 463552, "exercisedValue": 0, "unexercisedValue": 0}, {"maxAge": 1, "name": "Mr. Todd A. Nigro", "age": 55, "title": "Secretary & Vice Chairman", "yearBorn": 1969, "fiscalYear": 2024, "exercisedValue": 0, "unexercisedValue": 0}, {"maxAge": 1, "name": "Mr. Jeffery E. Whicker", "age": 52, "title": "Executive VP & CFO", "yearBorn": 1972, "fiscalYear": 2024, "totalPay": 402740, "exercisedValue": 0, "unexercisedValue": 1288000}, {"maxAge": 1, "name": "Mr. T. Ryan Sullivan", "age": 48, "title": "Executive Officer", "yearBorn": 1976, "fiscalYear": 2024, "totalPay": 637235, "exercisedValue": 0, "unexercisedValue": 0}, {"maxAge": 1, "name": "Mr. David J. Fersdahl", "age": 47, "title": "Executive VP of Cards & Payments of GBank", "yearBorn": 1977, "fiscalYear": 2024, "totalPay": 316744, "exercisedValue": 0, "unexercisedValue": 0}, {"maxAge": 1, "name": "Mr. Shouvik K. Ray", "age": 50, "title": "Executive VP and Chief Information & Technology Officer of GBank", "yearBorn": 1974, "fiscalYear": 2024, "totalPay": 275806, "exercisedValue": 0, "unexercisedValue": 0}, {"maxAge": 1, "name": "Mr. Scot M. Levine", "age": 45, "title": "Executive VP & Chief Risk Officer of GBank", "yearBorn": 1979, "fiscalYear": 2024, "totalPay": 216653, "exercisedValue": 0, "unexercisedValue": 0}, {"maxAge": 1, "name": "Ms. Nancy M. DeCou", "age": 66, "title": "Executive VP & Chief SBA Officer of GBank", "yearBorn": 1958, "fiscalYear": 2024, "totalPay": 4286609, "exercisedValue": 0, "unexercisedValue": 0}, {"maxAge": 1, "name": "Mr. Keith F. Jarvis", "age": 68, "title": "Executive VP & Chief Credit Officer of GBank", "yearBorn": 1956, "fiscalYear": 2024, "totalPay": 285972, "exercisedValue": 0, "unexercisedValue": 0}, {"maxAge": 1, "name": "Ms. Tara A. Campbell", "age": 44, "title": "Executive VP & COO at GBank", "yearBorn": 1980, "fiscalYear": 2024, "totalPay": 385610, "exercisedValue": 0, "unexercisedValue": 398190}], "auditRisk": 9, "boardRisk": 9, "compensationRisk": 9, "shareHolderRightsRisk": 6, "overallRisk": 9, "governanceEpochDate": 1761955200, "compensationAsOfEpochDate": 1735603200, "executiveTeam": [], "maxAge": 86400, "priceHint": 2, "previousClose": 34.55, "open": 34.69, "dayLow": 33.74, "dayHigh": 35.0, "regularMarketPreviousClose": 34.55, "regularMarketOpen": 34.69, "regularMarketDayLow": 33.74, "regularMarketDayHigh": 35.0, "payoutRatio": 0.0, "beta": -0.252, "trailingPE": 26.68504, "forwardPE": 21.864517, "volume": 67896, "regularMarketVolume": 67896, "averageVolume": 43361, "averageVolume10days": 60470, "averageDailyVolume10Day": 60470, "bid": 33.72, "ask": 34.44, "bidSize": 1, "askSize": 1, "marketCap": 487206464, "fiftyTwoWeekLow": 27.0, "fiftyTwoWeekHigh": 46.0, "allTimeHigh": 46.0, "allTimeLow": 16.435, "priceToSalesTrailing12Months": 7.226224, "fiftyDayAverage": 38.6979, "twoHundredDayAverage": 38.20916, "trailingAnnualDividendRate": 0.0, "trailingAnnualDividendYield": 0.0, "currency": "USD", "tradeable": false, "enterpriseValue": 415902464, "profitMargins": 0.2785, "floatShares": 8851085, "sharesOutstanding": 14376113, "sharesShort": 585781, "sharesShortPriorMonth": 588367, "sharesShortPreviousMonthDate": 1759190400, "dateShortInterest": 1761868800, "sharesPercentSharesOut": 0.040999997, "heldPercentInsiders": 0.35514, "heldPercentInstitutions": 0.22076, "shortRatio": 15.13, "shortPercentOfFloat": 0.0652, "impliedSharesOutstanding": 14376113, "bookValue": 11.072, "priceToBook": 3.0608745, "lastFiscalYearEnd": 1735603200, "nextFiscalYearEnd": 1767139200, "mostRecentQuarter": 1759190400, "earningsQuarterlyGrowth": -0.141, "netIncomeToCommon": 18777000, "trailingEps": 1.27, "forwardEps": 1.55, "enterpriseToRevenue": 6.169, "52WeekChange": 0.25226533, "SandP52WeekChange": 0.1276468, "quoteType": "EQUITY", "currentPrice": 33.89, "targetHighPrice": 55.0, "targetLowPrice": 50.0, "targetMeanPrice": 52.5, "targetMedianPrice": 52.5, "recommendationMean": 1.0, "recommendationKey": "strong_buy", "numberOfAnalystOpinions": 2, "totalCash": 103390000, "totalCashPerShare": 7.192, "totalDebt": 32086000, "totalRevenue": 67422000, "revenuePerShare": 4.739, "returnOnAssets": 0.01549, "returnOnEquity": 0.12564, "grossProfits": 67422000, "operatingCashflow": 22551000, "earningsGrowth": -0.211, "revenueGrowth": 0.152, "grossMargins": 0.0, "ebitdaMargins": 0.0, "operatingMargins": 0.32151002, "financialCurrency": "USD", "symbol": "GBFH", "language": "en-US", "region": "US", "typeDisp": "Equity", "quoteSourceName": "Nasdaq Real Time Price", "triggerable": true, "customPriceAlertConfidence": "HIGH", "ipoExpectedDate": "2025-04-30", "prevName": "GBank Financial Holdings, Inc.", "nameChangeDate": "2025-11-18", "averageAnalystRating": "1.0 - Strong Buy", "cryptoTradeable": false, "marketState": "PREPRE", "shortName": "GBank Financial Holdings Inc.", "longName": "GBank Financial Holdings Inc.", "hasPrePostMarketData": true, "firstTradeDateMilliseconds": 1720531800000, "postMarketChangePercent": 0.0, "postMarketPrice": 33.89, "postMarketChange": 0.0, "regularMarketChange": -0.66, "regularMarketDayRange": "33.74 - 35.0", "fullExchangeName": "NasdaqCM", "averageDailyVolume3Month": 43361, "fiftyTwoWeekLowChange": 6.8899994, "fiftyTwoWeekLowChangePercent": 0.25518516, "fiftyTwoWeekRange": "27.0 - 46.0", "fiftyTwoWeekHighChange": -12.110001, "fiftyTwoWeekHighChangePercent": -0.26326087, "fiftyTwoWeekChangePercent": 25.226534, "earningsTimestamp": 1761681600, "earningsTimestampStart": 1769547600, "earningsTimestampEnd": 1769547600, "earningsCallTimestampStart": 1761757200, "earningsCallTimestampEnd": 1761757200, "isEarningsDateEstimate": true, "epsTrailingTwelveMonths": 1.27, "epsForward": 1.55, "epsCurrentYear": 1.55, "priceEpsCurrentYear": 21.864517, "fiftyDayAverageChange": -4.8078995, "fiftyDayAverageChangePercent": -0.12424187, "twoHundredDayAverageChange": -4.3191605, "twoHundredDayAverageChangePercent": -0.113039926, "sourceInterval": 15, "exchangeDataDelayedBy": 0, "corporateActions": [], "postMarketTime": 1763499788, "regularMarketTime": 1763499600, "exchange": "NCM", "messageBoardId": "finmb_546499922", "exchangeTimezoneName": "America/New_York", "exchangeTimezoneShortName": "EST", "gmtOffSetMilliseconds": -18000000, "market": "us_market", "esgPopulated": false, "regularMarketChangePercent": -1.91027, "regularMarketPrice": 33.89, "displayName": "GBank Financial", "trailingPegRatio": null}, "info_ts": "2025-11-19T06:50:14.420395+00:00"}