{"info": {"address1": "22901 Millcreek Boulevard", "address2": "Suite 600", "city": "Cleveland", "state": "OH", "zip": "44122", "country": "United States", "phone": "440 229 5151", "website": "https://nacco.com", "industry": "Thermal Coal", "industryKey": "thermal-coal", "industryDisp": "Thermal Coal", "sector": "Energy", "sectorKey": "energy", "sectorDisp": "Energy", "longBusinessSummary": "NACCO Industries, Inc., together with its subsidiaries, engages in the natural resources business. The company operates through three segments: Coal Mining, North American Mining, and Minerals Management. The Coal Mining segment operates surface coal mines under long-term contracts with power generation companies. Coal is surface mined in North Dakota and Mississippi. The North American Mining segment provides value-added contract mining and other services for producers of aggregates, activated carbon, lithium, and other industrial minerals; and contract mining services for independently owned mines and quarries in Florida, Texas, Arkansas, Virginia, and Nebraska. The Minerals Management segment is involved in the leasing of its royalty and mineral interests to third-party exploration and production companies, and other mining companies, which grants them the rights to explore, develop, mine, produce, market, and sell gas, oil, and coal. The company was founded in 1913 and is headquartered in Cleveland, Ohio.", "fullTimeEmployees": 600, "companyOfficers": [{"maxAge": 1, "name": "Mr. John C. Butler Jr.", "age": 63, "title": "President, CEO & Non-Independent Director", "yearBorn": 1961, "fiscalYear": 2024, "totalPay": 3213720, "exercisedValue": 0, "unexercisedValue": 0}, {"maxAge": 1, "name": "Mr. Carroll L. Dewing", "age": 67, "title": "Senior VP & COO", "yearBorn": 1957, "fiscalYear": 2024, "totalPay": 937522, "exercisedValue": 0, "unexercisedValue": 0}, {"maxAge": 1, "name": "Mr. John D. Neumann", "age": 48, "title": "Senior VP, General Counsel & Secretary", "yearBorn": 1976, "fiscalYear": 2024, "totalPay": 887155, "exercisedValue": 0, "unexercisedValue": 0}, {"maxAge": 1, "name": "Mr. J. Patrick Sullivan Jr.", "age": 65, "title": "Senior VP & CFO", "yearBorn": 1959, "fiscalYear": 2024, "exercisedValue": 0, "unexercisedValue": 0}, {"maxAge": 1, "name": "Mr. Berry Philip Nathan", "age": 56, "title": "President of North American Mining", "yearBorn": 1968, "fiscalYear": 2024, "exercisedValue": 0, "unexercisedValue": 0}, {"maxAge": 1, "name": "Mr. Eric Scott Anderson Ph.D.", "age": 48, "title": "President of Mitigation Resources of North America", "yearBorn": 1976, "fiscalYear": 2024, "exercisedValue": 0, "unexercisedValue": 0}, {"maxAge": 1, "name": "Ms. Elizabeth I. Loveman CPA", "age": 54, "title": "Senior VP & Controller", "yearBorn": 1970, "fiscalYear": 2024, "totalPay": 421686, "exercisedValue": 0, "unexercisedValue": 0}, {"maxAge": 1, "name": "Mr. Robert O. Strenski", "age": 67, "title": "President of KC", "yearBorn": 1957, "fiscalYear": 2024, "exercisedValue": 0, "unexercisedValue": 0}, {"maxAge": 1, "name": "Mr. Thomas A. Maxwell", "age": 46, "title": "Senior VP of Finance & Treasurer", "yearBorn": 1978, "fiscalYear": 2024, "exercisedValue": 0, "unexercisedValue": 0}, {"maxAge": 1, "name": "Mr. Brian Matthew Larson", "age": 40, "title": "President of Catapult Mineral Partners, LLC & Director of Oil and Gas Development", "yearBorn": 1984, "fiscalYear": 2024, "exercisedValue": 0, "unexercisedValue": 0}], "auditRisk": 5, "boardRisk": 10, "compensationRisk": 7, "shareHolderRightsRisk": 10, "overallRisk": 10, "governanceEpochDate": 1761955200, "compensationAsOfEpochDate": 1735603200, "executiveTeam": [], "maxAge": 86400, "priceHint": 2, "previousClose": 52.69, "open": 53.16, "dayLow": 51.02, "dayHigh": 53.125, "regularMarketPreviousClose": 52.69, "regularMarketOpen": 53.16, "regularMarketDayLow": 51.02, "regularMarketDayHigh": 53.125, "dividendRate": 1.01, "dividendYield": 1.98, "exDividendDate": 1756771200, "payoutRatio": 0.2455, "fiveYearAvgDividendYield": 2.54, "beta": 0.494, "trailingPE": 13.0485935, "volume": 9508, "regularMarketVolume": 10021, "averageVolume": 10795, "averageVolume10days": 13580, "averageDailyVolume10Day": 13580, "bid": 0.0, "ask": 0.0, "bidSize": 400, "askSize": 100, "marketCap": 380606912, "fiftyTwoWeekLow": 27.47, "fiftyTwoWeekHigh": 53.88, "allTimeHigh": 66.4, "allTimeLow": 0.368441, "priceToSalesTrailing12Months": 1.3552543, "fiftyDayAverage": 43.118, "twoHundredDayAverage": 37.90595, "trailingAnnualDividendRate": 0.96, "trailingAnnualDividendYield": 0.018219776, "currency": "USD", "tradeable": false, "enterpriseValue": 415798912, "profitMargins": 0.10318, "floatShares": 4215695, "sharesOutstanding": 5897002, "sharesShort": 17183, "sharesShortPriorMonth": 17787, "sharesShortPreviousMonthDate": 1759190400, "dateShortInterest": 1761868800, "sharesPercentSharesOut": 0.0023, "heldPercentInsiders": 0.3206, "heldPercentInstitutions": 0.36569, "shortRatio": 1.7, "shortPercentOfFloat": 0.0034999999, "impliedSharesOutstanding": 7459955, "bookValue": 57.159, "priceToBook": 0.89259785, "lastFiscalYearEnd": 1735603200, "nextFiscalYearEnd": 1767139200, "mostRecentQuarter": 1759190400, "earningsQuarterlyGrowth": -0.152, "netIncomeToCommon": 28978000, "trailingEps": 3.91, "lastSplitFactor": "4377:1000", "lastSplitDate": 1506902400, "enterpriseToRevenue": 1.481, "enterpriseToEbitda": -20.028, "52WeekChange": 0.7522447, "SandP52WeekChange": 0.1276468, "lastDividendValue": 0.253, "lastDividendDate": 1756771200, "quoteType": "EQUITY", "currentPrice": 51.02, "recommendationKey": "none", "totalCash": 52657000, "totalCashPerShare": 7.059, "ebitda": -20761000, "totalDebt": 87849000, "quickRatio": 1.294, "currentRatio": 3.06, "totalRevenue": 280838016, "debtToEquity": 20.602, "revenuePerShare": 38.018, "returnOnAssets": -0.046090003, "returnOnEquity": 0.07036, "grossProfits": 34921000, "freeCashflow": -20980000, "operatingCashflow": 64670000, "earningsGrowth": -0.168, "revenueGrowth": 0.243, "grossMargins": 0.124350004, "ebitdaMargins": -0.07393, "operatingMargins": -0.13344, "financialCurrency": "USD", "symbol": "NC", "language": "en-US", "region": "US", "typeDisp": "Equity", "quoteSourceName": "Delayed Quote", "triggerable": true, "customPriceAlertConfidence": "HIGH", "corporateActions": [], "postMarketTime": 1763507410, "regularMarketTime": 1763499602, "exchange": "NYQ", "messageBoardId": "finmb_290291", "exchangeTimezoneName": "America/New_York", "exchangeTimezoneShortName": "EST", "gmtOffSetMilliseconds": -18000000, "market": "us_market", "esgPopulated": false, "regularMarketChangePercent": -3.16948, "regularMarketPrice": 51.02, "shortName": "NACCO Industries, Inc.", "marketState": "PREPRE", "fiftyDayAverageChange": 7.9020004, "fiftyDayAverageChangePercent": 0.18326454, "twoHundredDayAverageChange": 13.114052, "twoHundredDayAverageChangePercent": 0.3459629, "sourceInterval": 15, "exchangeDataDelayedBy": 0, "cryptoTradeable": false, "hasPrePostMarketData": true, "firstTradeDateMilliseconds": 235402200000, "postMarketChangePercent": 2.0188138, "postMarketPrice": 52.05, "postMarketChange": 1.0299988, "regularMarketChange": -1.67, "regularMarketDayRange": "51.02 - 53.125", "fullExchangeName": "NYSE", "averageDailyVolume3Month": 10795, "fiftyTwoWeekLowChange": 23.550001, "fiftyTwoWeekLowChangePercent": 0.8572989, "fiftyTwoWeekRange": "27.47 - 53.88", "fiftyTwoWeekHighChange": -2.8600006, "fiftyTwoWeekHighChangePercent": -0.05308093, "fiftyTwoWeekChangePercent": 75.22447, "dividendDate": 1757894400, "earningsTimestamp": 1762376400, "earningsTimestampStart": 1762376400, "earningsTimestampEnd": 1762376400, "earningsCallTimestampStart": 1761827400, "earningsCallTimestampEnd": 1761827400, "isEarningsDateEstimate": false, "epsTrailingTwelveMonths": 3.91, "longName": "NACCO Industries, Inc.", "displayName": "NACCO Industries", "trailingPegRatio": null}, "info_ts": "2025-11-19T06:50:29.101269+00:00"}